nonebot_plugin_p5generator/__init__.py
nonebot_plugin_p5generator/generator.py
nonebot_plugin_p5generator-0.1.4.dist-info/WHEEL
nonebot_plugin_p5generator-0.1.4.dist-info/METADATA
nonebot_plugin_p5generator-0.1.4.dist-info/RECORD
