Metadata-Version: 2.1
Name: nonebot-plugin-p5generator
Version: 0.1.4
Summary: A generator of persona5 chatbot based on nonebot2 framework
Author: xi-yue-233
Author-email: 1004514855@qq.com
Requires-Python: >=3.9,<4.0
Classifier: Programming Language :: Python :: 3
Classifier: Programming Language :: Python :: 3.9
Classifier: Programming Language :: Python :: 3.10
Classifier: Programming Language :: Python :: 3.11
Requires-Dist: nonebot-adapter-onebot (>=2.2.0,<3.0.0)
Requires-Dist: nonebot2 (>=2.0.0rc2,<3.0.0)
Requires-Dist: pillow (>=9.5.0,<10.0.0)
